dimc.cpython-311-x86_64-linux-gnu.so
dimcpp.cpython-311-x86_64-linux-gnu.so
dimbrowserwrappercpp.cpython-311-x86_64-linux-gnu.so
dimbrowser/__init__.py
dimbrowser/dimbrowser.py
pydim/__init__.py
pydim/debug.py
pydim3.libs/libdim-1557a5b5.so.v20r11
pydim3-3.0.6.dist-info/RECORD
pydim3-3.0.6.dist-info/WHEEL
pydim3-3.0.6.dist-info/top_level.txt
pydim3-3.0.6.dist-info/METADATA
