Metadata-Version: 2.1
Name: pydim3
Version: 3.0.6
Summary: Python interface package for DIM C and C++ interfaces.
Home-page: http://lhcbdoc.web.cern.ch/lhcbdoc/pydim/index.html
Author: Niko Neufeld (originally by Radu Stoica)
Author-email: niko.neufeld@cern.ch
License: GPL
Platform: UNKNOWN
Classifier: Programming Language :: Cython
Requires-Python: >=3
